datacubes/__init__.py
datacubes/cli.py
datacubes/datacubes.py
datacubes-0.1.1.dist-info/AUTHORS.rst
datacubes-0.1.1.dist-info/METADATA
datacubes-0.1.1.dist-info/WHEEL
datacubes-0.1.1.dist-info/entry_points.txt
datacubes-0.1.1.dist-info/top_level.txt
datacubes-0.1.1.dist-info/RECORD
