Metadata-Version: 2.1
Name: datacubes
Version: 0.1.1
Summary: A client library for InfoBlox DDI appliances.
Home-page: https://github.com/cmunetdev/datacubes
Author: Karim Benbourenane
Author-email: kbenbour@andrew.cmu.edu
License: UNKNOWN
Keywords: datacubes
Platform: UNKNOWN
Classifier: Development Status :: 2 - Pre-Alpha
Classifier: Intended Audience :: Developers
Classifier: Natural Language :: English
Classifier: Programming Language :: Python :: 3
Classifier: Programming Language :: Python :: 3.5
Classifier: Programming Language :: Python :: 3.6
Classifier: Programming Language :: Python :: 3.7
Classifier: Programming Language :: Python :: 3.8
Requires-Python: >=3.5
Requires-Dist: Click (>=7.0)
